smart_dummy
