Metadata-Version: 2.1
Name: smart-dummy
Version: 0.1.4
Summary: A smart and easy replacement to pandas.get_dummies() 
Home-page: https://github.com/emmalzhang/smart_dummy
Author: Muriel Grobler, Emma Zhang
Author-email: muriel.grobler@gmail.com, emma.lzhang@gmail.com
License: UNKNOWN
Platform: UNKNOWN
Classifier: License :: OSI Approved :: MIT License
Classifier: Programming Language :: Python
Classifier: Programming Language :: Python :: 3
Classifier: Programming Language :: Python :: 3.9
